hcdc-0.2.2.dist-info/licenses/AUTHORS
hcdc-0.2.2.dist-info/licenses/LICENSE
src/__init__.py
src/image_processing.py
src/main.py
src/text_processing.py
hcdc-0.2.2.dist-info/METADATA
hcdc-0.2.2.dist-info/WHEEL
hcdc-0.2.2.dist-info/entry_points.txt
hcdc-0.2.2.dist-info/pbr.json
hcdc-0.2.2.dist-info/top_level.txt
hcdc-0.2.2.dist-info/RECORD
